ensenso_nxlib/__init__.py
nxlib/__init__.py
nxlib/_helper.py
nxlib/api.py
nxlib/command.py
nxlib/constants.py
nxlib/context.py
nxlib/exception.py
nxlib/item.py
nxlib/log.py
nxlib-4.3.880.dist-info/LICENSE.md
nxlib-4.3.880.dist-info/LICENSE.md.in
nxlib-4.3.880.dist-info/METADATA
nxlib-4.3.880.dist-info/WHEEL
nxlib-4.3.880.dist-info/top_level.txt
nxlib-4.3.880.dist-info/RECORD
