Metadata-Version: 2.1
Name: nxlib
Version: 4.3.880
Summary: Python interface to interact with the Ensenso NxLib
Home-page: https://www.ensenso.com/python-api
Author: Optonic GmbH
Author-email: support@optonic.com
License: MIT
Platform: UNKNOWN
Classifier: Development Status :: 5 - Production/Stable
Classifier: License :: OSI Approved :: MIT License
Classifier: Programming Language :: Python :: 3
Requires-Python: >3.5.0
Requires-Dist: numpy
